project_provisioner/__init__.py
project_provisioner/cli.py
project_provisioner/core.py
tests/__init__.py
tests/conftest.py
tests/test_azure_cli_integration.py
tests/test_cli.py
tests/test_config.py
tests/test_core.py
project_provisioner-0.3.0.dist-info/METADATA
project_provisioner-0.3.0.dist-info/WHEEL
project_provisioner-0.3.0.dist-info/entry_points.txt
project_provisioner-0.3.0.dist-info/top_level.txt
project_provisioner-0.3.0.dist-info/RECORD
