Metadata-Version: 2.4
Name: project-provisioner
Version: 0.3.0
Summary: Uma ferramenta CLI para provisionar automaticamente novos projetos de dados no Azure DevOps e Databricks com integração completa ao Azure CLI.
Home-page: https://github.com/joseamaro/project-provisioner
Author: Jose Amaro
Author-email: jose.amarodev@gmail.com
Project-URL: Bug Reports, https://github.com/joseamaro/project-provisioner/issues
Project-URL: Source, https://github.com/joseamaro/project-provisioner
Keywords: databricks azure devops cli automation azure-cli
Classifier: Development Status :: 3 - Alpha
Classifier: Intended Audience :: Developers
Classifier: License :: OSI Approved :: MIT License
Classifier: Programming Language :: Python :: 3
Classifier: Programming Language :: Python :: 3.8
Classifier: Programming Language :: Python :: 3.9
Classifier: Programming Language :: Python :: 3.10
Classifier: Programming Language :: Python :: 3.11
Classifier: Programming Language :: Python :: 3.12
Classifier: Operating System :: OS Independent
Classifier: Topic :: Software Development :: Libraries :: Python Modules
Classifier: Topic :: System :: Systems Administration
Requires-Python: >=3.8
Requires-Dist: click
Requires-Dist: PyYAML
Provides-Extra: dev
Requires-Dist: pytest>=7.0.0; extra == "dev"
Requires-Dist: pytest-cov>=4.0.0; extra == "dev"
Requires-Dist: pytest-mock>=3.10.0; extra == "dev"
Requires-Dist: black>=23.0.0; extra == "dev"
Requires-Dist: flake8>=6.0.0; extra == "dev"
Requires-Dist: mypy>=1.0.0; extra == "dev"
Dynamic: author
Dynamic: author-email
Dynamic: classifier
Dynamic: description
Dynamic: description-content-type
Dynamic: home-page
Dynamic: keywords
Dynamic: project-url
Dynamic: provides-extra
Dynamic: requires-dist
Dynamic: requires-python
Dynamic: summary
